README.md
setup.py
sequence_field/__init__.py
sequence_field/constants.py
sequence_field/error.py
sequence_field/expanders.py
sequence_field/fields.py
sequence_field/utils.py
sequence_field.egg-info/PKG-INFO
sequence_field.egg-info/SOURCES.txt
sequence_field.egg-info/dependency_links.txt
sequence_field.egg-info/requires.txt
sequence_field.egg-info/top_level.txt