Metadata-Version: 2.1
Name: sequence-field
Version: 1.0.5
Summary: flask sqlalchemy sequence field
Home-page: UNKNOWN
Author: Alan Zhang
Author-email: 1095087479@qq.com
License: UNKNOWN
Platform: UNKNOWN
Classifier: Programming Language :: Python :: 3
Classifier: License :: OSI Approved :: MIT License
Classifier: Operating System :: OS Independent
